{
    "nav-about": "Acerca",
    "nav-projects": "Proyectos",
    "nav-skills": "Habilidades",
    "nav-contact":"Contacto",
    "tit-about":"Acerca de mi",
    "tex-about":"Como desarrollador Full Stack con dos años de experiencia, he colaborado con diversos clientes, especializándome en el desarrollo de aplicaciones web y móviles. Además, como Arquitecto DevOps, he optimizado procesos de desarrollo y despliegue en la nube utilizando tecnologías como AWS, Azure y Google Cloud Platform. Mi enfoque es asegurar la entrega exitosa de proyectos, cumpliendo con estándares de calidad y plazos establecidos.",
    "tit-projects":"Proyectos",
    "card1-tit":"Proyecto Veterinaria Moka",
    "card1-tex":"Este proyecto fue diseñado para la materia de universidad ' Proyecto de Ingeniería de Software 1 '.",
    "card2-tit":"Sistema de gestión para Aereopuertos",
    "card2-tex":"Este proyecto fue diseñado para la materia de universidad ' Progrmación Orientada a Objetos '.",
    "card3-tit":"Sistema de Eventos - EventWizz",
    "card3-tex":"Este proyecto fue diseñado para la materia de universidad ' Proyecto de Ingeniería de Software 2 '.",
    "card4-tit":"Red Social Linkup",
    "card4-tex":"Este proyecto fue diseñado para la materia de universidad ' Diseño y construcción de componentes '.",
    "card5-tit":"Sistema de Gestión de Cursos",
    "card5-tex":"Sistema creado con el objetivo de dar seguimiento y asignar cursos a un grupo específico de personas.",
    "card6-tit":"Sistema de Facturacion",
    "card6-tex":"Sistema creado con el objetivo de tener un control de inventario y facturar dichos productos.",
    "tit-skills":"Habilidades",
    "tit-contact":"Contactame",
    "tex-contact":"Si tienes alguna pregunta, comentarios o una propuesta de colaboración, puedes contactarme enviándome un mensaje.",
    "form-name":"Nombre",
    "form-email":"Correo",
    "form-message":"Mensaje",
    "form-send":"Enviar",
    "contact-error-title":"Error",
    "contact-error-text":"Ocurrio un error al enviar el correo...",
    "contact-success-title":"El correo se ha enviado correctamente!"
  }
  